llm_anygate/__init__.py
llm_anygate/cli_tool.py
llm_anygate/config_converter.py
llm_anygate/litellm_checker.py
llm_anygate/proxy_generator.py
llm_anygate/templates.py
llm_anygate-1.0.4.dist-info/METADATA
llm_anygate-1.0.4.dist-info/WHEEL
llm_anygate-1.0.4.dist-info/entry_points.txt
llm_anygate-1.0.4.dist-info/licenses/LICENSE
llm_anygate-1.0.4.dist-info/RECORD
