Metadata-Version: 2.4
Name: llm-anygate
Version: 1.0.4
Summary: A flexible gateway for connecting and managing multiple LLM providers
Project-URL: Homepage, https://github.com/igamenovoer/llm-anygate
Project-URL: Repository, https://github.com/igamenovoer/llm-anygate
Project-URL: Issues, https://github.com/igamenovoer/llm-anygate/issues
Author-email: igamenovoer <igamenovoer@github.com>
License: MIT License
License-File: LICENSE
Keywords: ai,anthropic,api,gateway,llm,openai
Classifier: Development Status :: 3 - Alpha
Classifier: Intended Audience :: Developers
Classifier: License :: OSI Approved :: MIT License
Classifier: Programming Language :: Python :: 3
Classifier: Programming Language :: Python :: 3.11
Classifier: Programming Language :: Python :: 3.12
Classifier: Programming Language :: Python :: 3.13
Classifier: Topic :: Scientific/Engineering :: Artificial Intelligence
Classifier: Topic :: Software Development :: Libraries :: Python Modules
Requires-Python: >=3.11
Requires-Dist: click<9,>=8.2.1
Requires-Dist: fastapi>=0.100.0
Requires-Dist: httpx>=0.24.0
Requires-Dist: omegaconf<3,>=2.3.0
Requires-Dist: pydantic>=2.0.0
Requires-Dist: pyyaml>=6.0
Requires-Dist: uvicorn>=0.23.0
